CEM_LinearInf/__init__.py
CEM_LinearInf/balance.py
CEM_LinearInf/cem.py
CEM_LinearInf/data_generation.py
CEM_LinearInf/inference.py
CEM_LinearInf/sensitivity_analysis.py
CEM_LinearInf-0.0.1.dist-info/METADATA
CEM_LinearInf-0.0.1.dist-info/WHEEL
CEM_LinearInf-0.0.1.dist-info/top_level.txt
CEM_LinearInf-0.0.1.dist-info/RECORD
