Metadata-Version: 2.1
Name: CEM-LinearInf
Version: 0.0.1
Summary: CEM-LinearInf is a Python package for linear causal inference, which can help you implement the whole process of causal inference easily.
Author: WenyiWU0111
Classifier: Programming Language :: Python :: 3
Classifier: License :: OSI Approved :: MIT License
Classifier: Operating System :: OS Independent
Requires-Python: >=3.6
Requires-Dist: numpy
Requires-Dist: pandas
Requires-Dist: scipy (>=1.11.1)
Requires-Dist: scikit-learn
Requires-Dist: statsmodels
Requires-Dist: matplotlib
Requires-Dist: seaborn
